paapi5_python_sdk/__init__.py
paapi5_python_sdk/api_client.py
paapi5_python_sdk/availability.py
paapi5_python_sdk/browse_node.py
paapi5_python_sdk/browse_node_ancestor.py
paapi5_python_sdk/browse_node_child.py
paapi5_python_sdk/browse_node_children.py
paapi5_python_sdk/browse_node_info.py
paapi5_python_sdk/browse_nodes_result.py
paapi5_python_sdk/by_line_info.py
paapi5_python_sdk/classifications.py
paapi5_python_sdk/condition.py
paapi5_python_sdk/configuration.py
paapi5_python_sdk/content_info.py
paapi5_python_sdk/content_rating.py
paapi5_python_sdk/contributor.py
paapi5_python_sdk/delivery_flag.py
paapi5_python_sdk/dimension_based_attribute.py
paapi5_python_sdk/duration_price.py
paapi5_python_sdk/error_data.py
paapi5_python_sdk/external_ids.py
paapi5_python_sdk/get_browse_nodes_request.py
paapi5_python_sdk/get_browse_nodes_resource.py
paapi5_python_sdk/get_browse_nodes_response.py
paapi5_python_sdk/get_items_request.py
paapi5_python_sdk/get_items_resource.py
paapi5_python_sdk/get_items_response.py
paapi5_python_sdk/get_variations_request.py
paapi5_python_sdk/get_variations_resource.py
paapi5_python_sdk/get_variations_response.py
paapi5_python_sdk/image_size.py
paapi5_python_sdk/image_type.py
paapi5_python_sdk/images.py
paapi5_python_sdk/item.py
paapi5_python_sdk/item_id_type.py
paapi5_python_sdk/item_info.py
paapi5_python_sdk/items_result.py
paapi5_python_sdk/language_type.py
paapi5_python_sdk/languages.py
paapi5_python_sdk/manufacture_info.py
paapi5_python_sdk/max_price.py
paapi5_python_sdk/merchant.py
paapi5_python_sdk/min_price.py
paapi5_python_sdk/min_reviews_rating.py
paapi5_python_sdk/min_saving_percent.py
paapi5_python_sdk/multi_valued_attribute.py
paapi5_python_sdk/offer_availability.py
paapi5_python_sdk/offer_condition.py
paapi5_python_sdk/offer_count.py
paapi5_python_sdk/offer_delivery_info.py
paapi5_python_sdk/offer_listing.py
paapi5_python_sdk/offer_loyalty_points.py
paapi5_python_sdk/offer_merchant_info.py
paapi5_python_sdk/offer_price.py
amazon_api_forked-1.0.0.dist-info/COPYING.txt
amazon_api_forked-1.0.0.dist-info/LICENSE.txt
amazon_api_forked-1.0.0.dist-info/METADATA
amazon_api_forked-1.0.0.dist-info/NOTICE.txt
amazon_api_forked-1.0.0.dist-info/WHEEL
amazon_api_forked-1.0.0.dist-info/top_level.txt
amazon_api_forked-1.0.0.dist-info/RECORD
