Metadata-Version: 2.1
Name: amazon-api-forked
Version: 1.0.0
Summary: ProductAdvertisingAPI 5.0 Python SDK
Home-page: https://github.com/LeilaSchooley/paapi5-python-sdk
Author-email: 
License: Apache License 2.0
Keywords: ProductAdvertisingAPI,pa-api,paapi,amazon
License-File: LICENSE.txt
License-File: COPYING.txt
License-File: NOTICE.txt
Requires-Dist: urllib3 >=1.15
Requires-Dist: six >=1.10
Requires-Dist: certifi
Requires-Dist: python-dateutil
